Workbook

Sheet Unit costs per bisect
A1: Unit costs per bisect
A2: Pricing comparison · Main Scenario
A4: Variable / dimension | B4: LLM cost per run | C4: Stage run rate | D4: LLM cost per bisect
A5: Bisect (v2) | B5: =0.252 -> 0.252 | C5: =1 -> 1 | D5: ='Unit costs per bisect'!B5*'Unit costs per bisect'!C5 -> 0.252
A6: Fix & verify | B6: =0.3337 -> 0.3337 | C6: =0 -> 0 | D6: ='Unit costs per bisect'!B6*'Unit costs per bisect'!C6 -> 0
A7: Localise | B7: =0.2002 -> 0.2002 | C7: =0 -> 0 | D7: ='Unit costs per bisect'!B7*'Unit costs per bisect'!C7 -> 0

Sheet Billing assumptions
A1: Billing assumptions
A2: Pricing comparison · Main Scenario
A4: Variable / dimension | B4: Value
A5: Repos per customer | B5: =1 -> 1
A6: Card fee rate | B6: =0.029 -> 0.029
A7: Card fee per invoice | B7: =0.3 -> 0.3

Sheet Pricing plans
A1: Pricing plans
A2: Pricing comparison · Main Scenario
A4: Variable / dimension | B4: Price per repo | C4: Price per bisect | D4: Customer pays LLM
A5: A · Flat $199/repo | B5: =199 -> 199 | C5: =0 -> 0 | D5: =0 -> 0
A6: A · Flat $49/repo | B6: =49 -> 49 | C6: =0 -> 0 | D6: =0 -> 0
A7: B · BYOK + $99/repo | B7: =99 -> 99 | C7: =0 -> 0 | D7: =1 -> 1
A8: C · $5 per bisect | B8: =0 -> 0 | C8: =5 -> 5 | D8: =0 -> 0

Sheet Bisect volumes
A1: Bisect volumes
A2: Pricing comparison · Main Scenario
A4: Variable / dimension | B4: Bisects per month
A5: 10 bisects/mo | B5: =10 -> 10
A6: 200 bisects/mo | B6: =200 -> 200
A7: 50 bisects/mo | B7: =50 -> 50

Sheet Gross margin per customer
A1: Gross margin per customer
A2: Pricing comparison · Main Scenario
A4: Variable / dimension | B4: 10 bisects/mo | C4: 50 bisects/mo | D4: 200 bisects/mo
A5: Revenue per customer | B5: ="" | C5: ="" | D5: =""
A6: A · Flat $199/repo | B6: ='Billing assumptions'!B5*'Pricing plans'!B5+'Pricing plans'!C5*'Bisect volumes'!B5 -> 199 | C6: ='Billing assumptions'!B5*'Pricing plans'!B5+'Pricing plans'!C5*'Bisect volumes'!B7 -> 199 | D6: ='Billing assumptions'!B5*'Pricing plans'!B5+'Pricing plans'!C5*'Bisect volumes'!B6 -> 199
A7: A · Flat $49/repo | B7: ='Billing assumptions'!B5*'Pricing plans'!B6+'Pricing plans'!C6*'Bisect volumes'!B5 -> 49 | C7: ='Billing assumptions'!B5*'Pricing plans'!B6+'Pricing plans'!C6*'Bisect volumes'!B7 -> 49 | D7: ='Billing assumptions'!B5*'Pricing plans'!B6+'Pricing plans'!C6*'Bisect volumes'!B6 -> 49
A8: B · BYOK + $99/repo | B8: ='Billing assumptions'!B5*'Pricing plans'!B7+'Pricing plans'!C7*'Bisect volumes'!B5 -> 99 | C8: ='Billing assumptions'!B5*'Pricing plans'!B7+'Pricing plans'!C7*'Bisect volumes'!B7 -> 99 | D8: ='Billing assumptions'!B5*'Pricing plans'!B7+'Pricing plans'!C7*'Bisect volumes'!B6 -> 99
A9: C · $5 per bisect | B9: ='Billing assumptions'!B5*'Pricing plans'!B8+'Pricing plans'!C8*'Bisect volumes'!B5 -> 50 | C9: ='Billing assumptions'!B5*'Pricing plans'!B8+'Pricing plans'!C8*'Bisect volumes'!B7 -> 250 | D9: ='Billing assumptions'!B5*'Pricing plans'!B8+'Pricing plans'!C8*'Bisect volumes'!B6 -> 1000
A10: LLM cost per customer | B10: ="" | C10: ="" | D10: =""
A11: A · Flat $199/repo | B11: =(1-'Pricing plans'!D5)*'Bisect volumes'!B5*SUM('Unit costs per bisect'!D5,'Unit costs per bisect'!D6,'Unit costs per bisect'!D7) -> 2.52 | C11: =(1-'Pricing plans'!D5)*'Bisect volumes'!B7*SUM('Unit costs per bisect'!D5,'Unit costs per bisect'!D6,'Unit costs per bisect'!D7) -> 12.6 | D11: =(1-'Pricing plans'!D5)*'Bisect volumes'!B6*SUM('Unit costs per bisect'!D5,'Unit costs per bisect'!D6,'Unit costs per bisect'!D7) -> 50.4
A12: A · Flat $49/repo | B12: =(1-'Pricing plans'!D6)*'Bisect volumes'!B5*SUM('Unit costs per bisect'!D5,'Unit costs per bisect'!D6,'Unit costs per bisect'!D7) -> 2.52 | C12: =(1-'Pricing plans'!D6)*'Bisect volumes'!B7*SUM('Unit costs per bisect'!D5,'Unit costs per bisect'!D6,'Unit costs per bisect'!D7) -> 12.6 | D12: =(1-'Pricing plans'!D6)*'Bisect volumes'!B6*SUM('Unit costs per bisect'!D5,'Unit costs per bisect'!D6,'Unit costs per bisect'!D7) -> 50.4
A13: B · BYOK + $99/repo | B13: =(1-'Pricing plans'!D7)*'Bisect volumes'!B5*SUM('Unit costs per bisect'!D5,'Unit costs per bisect'!D6,'Unit costs per bisect'!D7) -> 0 | C13: =(1-'Pricing plans'!D7)*'Bisect volumes'!B7*SUM('Unit costs per bisect'!D5,'Unit costs per bisect'!D6,'Unit costs per bisect'!D7) -> 0 | D13: =(1-'Pricing plans'!D7)*'Bisect volumes'!B6*SUM('Unit costs per bisect'!D5,'Unit costs per bisect'!D6,'Unit costs per bisect'!D7) -> 0
A14: C · $5 per bisect | B14: =(1-'Pricing plans'!D8)*'Bisect volumes'!B5*SUM('Unit costs per bisect'!D5,'Unit costs per bisect'!D6,'Unit costs per bisect'!D7) -> 2.52 | C14: =(1-'Pricing plans'!D8)*'Bisect volumes'!B7*SUM('Unit costs per bisect'!D5,'Unit costs per bisect'!D6,'Unit costs per bisect'!D7) -> 12.6 | D14: =(1-'Pricing plans'!D8)*'Bisect volumes'!B6*SUM('Unit costs per bisect'!D5,'Unit costs per bisect'!D6,'Unit costs per bisect'!D7) -> 50.4
A15: Card fees per customer | B15: ="" | C15: ="" | D15: =""
A16: A · Flat $199/repo | B16: =IF(IF(IF(ISERROR('Gross margin per customer'!B6>0),'Gross margin per customer'!B6>0,IF('Gross margin per customer'!B6="","",'Gross margin per customer'!B6>0))="",FALSE,IF(ISERROR('Gross margin per customer'!B6>0),'Gross margin per customer'!B6>0,IF('Gross margin per customer'!B6="","",'Gross margin per customer'!B6>0))),'Gross margin per customer'!B6*'Billing assumptions'!B6+'Billing assumptions'!B7,0) -> 6.071 | C16: =IF(IF(IF(ISERROR('Gross margin per customer'!C6>0),'Gross margin per customer'!C6>0,IF('Gross margin per customer'!C6="","",'Gross margin per customer'!C6>0))="",FALSE,IF(ISERROR('Gross margin per customer'!C6>0),'Gross margin per customer'!C6>0,IF('Gross margin per customer'!C6="","",'Gross margin per customer'!C6>0))),'Gross margin per customer'!C6*'Billing assumptions'!B6+'Billing assumptions'!B7,0) -> 6.071 | D16: =IF(IF(IF(ISERROR('Gross margin per customer'!D6>0),'Gross margin per customer'!D6>0,IF('Gross margin per customer'!D6="","",'Gross margin per customer'!D6>0))="",FALSE,IF(ISERROR('Gross margin per customer'!D6>0),'Gross margin per customer'!D6>0,IF('Gross margin per customer'!D6="","",'Gross margin per customer'!D6>0))),'Gross margin per customer'!D6*'Billing assumptions'!B6+'Billing assumptions'!B7,0) -> 6.071
A17: A · Flat $49/repo | B17: =IF(IF(IF(ISERROR('Gross margin per customer'!B7>0),'Gross margin per customer'!B7>0,IF('Gross margin per customer'!B7="","",'Gross margin per customer'!B7>0))="",FALSE,IF(ISERROR('Gross margin per customer'!B7>0),'Gross margin per customer'!B7>0,IF('Gross margin per customer'!B7="","",'Gross margin per customer'!B7>0))),'Gross margin per customer'!B7*'Billing assumptions'!B6+'Billing assumptions'!B7,0) -> 1.721 | C17: =IF(IF(IF(ISERROR('Gross margin per customer'!C7>0),'Gross margin per customer'!C7>0,IF('Gross margin per customer'!C7="","",'Gross margin per customer'!C7>0))="",FALSE,IF(ISERROR('Gross margin per customer'!C7>0),'Gross margin per customer'!C7>0,IF('Gross margin per customer'!C7="","",'Gross margin per customer'!C7>0))),'Gross margin per customer'!C7*'Billing assumptions'!B6+'Billing assumptions'!B7,0) -> 1.721 | D17: =IF(IF(IF(ISERROR('Gross margin per customer'!D7>0),'Gross margin per customer'!D7>0,IF('Gross margin per customer'!D7="","",'Gross margin per customer'!D7>0))="",FALSE,IF(ISERROR('Gross margin per customer'!D7>0),'Gross margin per customer'!D7>0,IF('Gross margin per customer'!D7="","",'Gross margin per customer'!D7>0))),'Gross margin per customer'!D7*'Billing assumptions'!B6+'Billing assumptions'!B7,0) -> 1.721
A18: B · BYOK + $99/repo | B18: =IF(IF(IF(ISERROR('Gross margin per customer'!B8>0),'Gross margin per customer'!B8>0,IF('Gross margin per customer'!B8="","",'Gross margin per customer'!B8>0))="",FALSE,IF(ISERROR('Gross margin per customer'!B8>0),'Gross margin per customer'!B8>0,IF('Gross margin per customer'!B8="","",'Gross margin per customer'!B8>0))),'Gross margin per customer'!B8*'Billing assumptions'!B6+'Billing assumptions'!B7,0) -> 3.171 | C18: =IF(IF(IF(ISERROR('Gross margin per customer'!C8>0),'Gross margin per customer'!C8>0,IF('Gross margin per customer'!C8="","",'Gross margin per customer'!C8>0))="",FALSE,IF(ISERROR('Gross margin per customer'!C8>0),'Gross margin per customer'!C8>0,IF('Gross margin per customer'!C8="","",'Gross margin per customer'!C8>0))),'Gross margin per customer'!C8*'Billing assumptions'!B6+'Billing assumptions'!B7,0) -> 3.171 | D18: =IF(IF(IF(ISERROR('Gross margin per customer'!D8>0),'Gross margin per customer'!D8>0,IF('Gross margin per customer'!D8="","",'Gross margin per customer'!D8>0))="",FALSE,IF(ISERROR('Gross margin per customer'!D8>0),'Gross margin per customer'!D8>0,IF('Gross margin per customer'!D8="","",'Gross margin per customer'!D8>0))),'Gross margin per customer'!D8*'Billing assumptions'!B6+'Billing assumptions'!B7,0) -> 3.171
A19: C · $5 per bisect | B19: =IF(IF(IF(ISERROR('Gross margin per customer'!B9>0),'Gross margin per customer'!B9>0,IF('Gross margin per customer'!B9="","",'Gross margin per customer'!B9>0))="",FALSE,IF(ISERROR('Gross margin per customer'!B9>0),'Gross margin per customer'!B9>0,IF('Gross margin per customer'!B9="","",'Gross margin per customer'!B9>0))),'Gross margin per customer'!B9*'Billing assumptions'!B6+'Billing assumptions'!B7,0) -> 1.75 | C19: =IF(IF(IF(ISERROR('Gross margin per customer'!C9>0),'Gross margin per customer'!C9>0,IF('Gross margin per customer'!C9="","",'Gross margin per customer'!C9>0))="",FALSE,IF(ISERROR('Gross margin per customer'!C9>0),'Gross margin per customer'!C9>0,IF('Gross margin per customer'!C9="","",'Gross margin per customer'!C9>0))),'Gross margin per customer'!C9*'Billing assumptions'!B6+'Billing assumptions'!B7,0) -> 7.55 | D19: =IF(IF(IF(ISERROR('Gross margin per customer'!D9>0),'Gross margin per customer'!D9>0,IF('Gross margin per customer'!D9="","",'Gross margin per customer'!D9>0))="",FALSE,IF(ISERROR('Gross margin per customer'!D9>0),'Gross margin per customer'!D9>0,IF('Gross margin per customer'!D9="","",'Gross margin per customer'!D9>0))),'Gross margin per customer'!D9*'Billing assumptions'!B6+'Billing assumptions'!B7,0) -> 29.3
A20: Gross profit per customer | B20: ="" | C20: ="" | D20: =""
A21: A · Flat $199/repo | B21: ='Gross margin per customer'!B6-'Gross margin per customer'!B11-'Gross margin per customer'!B16 -> 190.409 | C21: ='Gross margin per customer'!C6-'Gross margin per customer'!C11-'Gross margin per customer'!C16 -> 180.329 | D21: ='Gross margin per customer'!D6-'Gross margin per customer'!D11-'Gross margin per customer'!D16 -> 142.529
A22: A · Flat $49/repo | B22: ='Gross margin per customer'!B7-'Gross margin per customer'!B12-'Gross margin per customer'!B17 -> 44.759 | C22: ='Gross margin per customer'!C7-'Gross margin per customer'!C12-'Gross margin per customer'!C17 -> 34.679 | D22: ='Gross margin per customer'!D7-'Gross margin per customer'!D12-'Gross margin per customer'!D17 -> -3.121
A23: B · BYOK + $99/repo | B23: ='Gross margin per customer'!B8-'Gross margin per customer'!B13-'Gross margin per customer'!B18 -> 95.829 | C23: ='Gross margin per customer'!C8-'Gross margin per customer'!C13-'Gross margin per customer'!C18 -> 95.829 | D23: ='Gross margin per customer'!D8-'Gross margin per customer'!D13-'Gross margin per customer'!D18 -> 95.829
A24: C · $5 per bisect | B24: ='Gross margin per customer'!B9-'Gross margin per customer'!B14-'Gross margin per customer'!B19 -> 45.73 | C24: ='Gross margin per customer'!C9-'Gross margin per customer'!C14-'Gross margin per customer'!C19 -> 229.85 | D24: ='Gross margin per customer'!D9-'Gross margin per customer'!D14-'Gross margin per customer'!D19 -> 920.3
A25: Gross margin % | B25: ="" | C25: ="" | D25: =""
A26: A · Flat $199/repo | B26: =IFERROR('Gross margin per customer'!B21/'Gross margin per customer'!B6,"") -> 0.95682915 | C26: =IFERROR('Gross margin per customer'!C21/'Gross margin per customer'!C6,"") -> 0.90617588 | D26: =IFERROR('Gross margin per customer'!D21/'Gross margin per customer'!D6,"") -> 0.71622613
A27: A · Flat $49/repo | B27: =IFERROR('Gross margin per customer'!B22/'Gross margin per customer'!B7,"") -> 0.91344898 | C27: =IFERROR('Gross margin per customer'!C22/'Gross margin per customer'!C7,"") -> 0.70773469 | D27: =IFERROR('Gross margin per customer'!D22/'Gross margin per customer'!D7,"") -> -0.063693878
A28: B · BYOK + $99/repo | B28: =IFERROR('Gross margin per customer'!B23/'Gross margin per customer'!B8,"") -> 0.9679697 | C28: =IFERROR('Gross margin per customer'!C23/'Gross margin per customer'!C8,"") -> 0.9679697 | D28: =IFERROR('Gross margin per customer'!D23/'Gross margin per customer'!D8,"") -> 0.9679697
A29: C · $5 per bisect | B29: =IFERROR('Gross margin per customer'!B24/'Gross margin per customer'!B9,"") -> 0.9146 | C29: =IFERROR('Gross margin per customer'!C24/'Gross margin per customer'!C9,"") -> 0.9194 | D29: =IFERROR('Gross margin per customer'!D24/'Gross margin per customer'!D9,"") -> 0.9203

Sheet Break-even inputs
A1: Break-even inputs
A2: Pricing comparison · Main Scenario
A4: Variable / dimension | B4: Value
A5: Founders | B5: =2 -> 2
A6: Founder cost per month | B6: =5000 -> 5000
A7: Other fixed costs per month | B7: =500 -> 500
A8: Monthly fixed costs | B8: ='Break-even inputs'!B5*'Break-even inputs'!B6+'Break-even inputs'!B7 -> 10500

Sheet Break-even paying repos
A1: Break-even paying repos
A2: Pricing comparison · Main Scenario
A4: Variable / dimension | B4: 10 bisects/mo | C4: 50 bisects/mo | D4: 200 bisects/mo
A5: Break-even paying repos | B5: ="" | C5: ="" | D5: =""
A6: A · Flat $199/repo | B6: =IF(IF(IF(ISERROR('Gross margin per customer'!B21>0),'Gross margin per customer'!B21>0,IF('Gross margin per customer'!B21="","",'Gross margin per customer'!B21>0))="",FALSE,IF(ISERROR('Gross margin per customer'!B21>0),'Gross margin per customer'!B21>0,IF('Gross margin per customer'!B21="","",'Gross margin per customer'!B21>0))),CEILING('Break-even inputs'!B8/('Gross margin per customer'!B21/'Billing assumptions'!B5),1),"") -> 56 | C6: =IF(IF(IF(ISERROR('Gross margin per customer'!C21>0),'Gross margin per customer'!C21>0,IF('Gross margin per customer'!C21="","",'Gross margin per customer'!C21>0))="",FALSE,IF(ISERROR('Gross margin per customer'!C21>0),'Gross margin per customer'!C21>0,IF('Gross margin per customer'!C21="","",'Gross margin per customer'!C21>0))),CEILING('Break-even inputs'!B8/('Gross margin per customer'!C21/'Billing assumptions'!B5),1),"") -> 59 | D6: =IF(IF(IF(ISERROR('Gross margin per customer'!D21>0),'Gross margin per customer'!D21>0,IF('Gross margin per customer'!D21="","",'Gross margin per customer'!D21>0))="",FALSE,IF(ISERROR('Gross margin per customer'!D21>0),'Gross margin per customer'!D21>0,IF('Gross margin per customer'!D21="","",'Gross margin per customer'!D21>0))),CEILING('Break-even inputs'!B8/('Gross margin per customer'!D21/'Billing assumptions'!B5),1),"") -> 74
A7: A · Flat $49/repo | B7: =IF(IF(IF(ISERROR('Gross margin per customer'!B22>0),'Gross margin per customer'!B22>0,IF('Gross margin per customer'!B22="","",'Gross margin per customer'!B22>0))="",FALSE,IF(ISERROR('Gross margin per customer'!B22>0),'Gross margin per customer'!B22>0,IF('Gross margin per customer'!B22="","",'Gross margin per customer'!B22>0))),CEILING('Break-even inputs'!B8/('Gross margin per customer'!B22/'Billing assumptions'!B5),1),"") -> 235 | C7: =IF(IF(IF(ISERROR('Gross margin per customer'!C22>0),'Gross margin per customer'!C22>0,IF('Gross margin per customer'!C22="","",'Gross margin per customer'!C22>0))="",FALSE,IF(ISERROR('Gross margin per customer'!C22>0),'Gross margin per customer'!C22>0,IF('Gross margin per customer'!C22="","",'Gross margin per customer'!C22>0))),CEILING('Break-even inputs'!B8/('Gross margin per customer'!C22/'Billing assumptions'!B5),1),"") -> 303 | D7: =IF(IF(IF(ISERROR('Gross margin per customer'!D22>0),'Gross margin per customer'!D22>0,IF('Gross margin per customer'!D22="","",'Gross margin per customer'!D22>0))="",FALSE,IF(ISERROR('Gross margin per customer'!D22>0),'Gross margin per customer'!D22>0,IF('Gross margin per customer'!D22="","",'Gross margin per customer'!D22>0))),CEILING('Break-even inputs'!B8/('Gross margin per customer'!D22/'Billing assumptions'!B5),1),"")
A8: B · BYOK + $99/repo | B8: =IF(IF(IF(ISERROR('Gross margin per customer'!B23>0),'Gross margin per customer'!B23>0,IF('Gross margin per customer'!B23="","",'Gross margin per customer'!B23>0))="",FALSE,IF(ISERROR('Gross margin per customer'!B23>0),'Gross margin per customer'!B23>0,IF('Gross margin per customer'!B23="","",'Gross margin per customer'!B23>0))),CEILING('Break-even inputs'!B8/('Gross margin per customer'!B23/'Billing assumptions'!B5),1),"") -> 110 | C8: =IF(IF(IF(ISERROR('Gross margin per customer'!C23>0),'Gross margin per customer'!C23>0,IF('Gross margin per customer'!C23="","",'Gross margin per customer'!C23>0))="",FALSE,IF(ISERROR('Gross margin per customer'!C23>0),'Gross margin per customer'!C23>0,IF('Gross margin per customer'!C23="","",'Gross margin per customer'!C23>0))),CEILING('Break-even inputs'!B8/('Gross margin per customer'!C23/'Billing assumptions'!B5),1),"") -> 110 | D8: =IF(IF(IF(ISERROR('Gross margin per customer'!D23>0),'Gross margin per customer'!D23>0,IF('Gross margin per customer'!D23="","",'Gross margin per customer'!D23>0))="",FALSE,IF(ISERROR('Gross margin per customer'!D23>0),'Gross margin per customer'!D23>0,IF('Gross margin per customer'!D23="","",'Gross margin per customer'!D23>0))),CEILING('Break-even inputs'!B8/('Gross margin per customer'!D23/'Billing assumptions'!B5),1),"") -> 110
A9: C · $5 per bisect | B9: =IF(IF(IF(ISERROR('Gross margin per customer'!B24>0),'Gross margin per customer'!B24>0,IF('Gross margin per customer'!B24="","",'Gross margin per customer'!B24>0))="",FALSE,IF(ISERROR('Gross margin per customer'!B24>0),'Gross margin per customer'!B24>0,IF('Gross margin per customer'!B24="","",'Gross margin per customer'!B24>0))),CEILING('Break-even inputs'!B8/('Gross margin per customer'!B24/'Billing assumptions'!B5),1),"") -> 230 | C9: =IF(IF(IF(ISERROR('Gross margin per customer'!C24>0),'Gross margin per customer'!C24>0,IF('Gross margin per customer'!C24="","",'Gross margin per customer'!C24>0))="",FALSE,IF(ISERROR('Gross margin per customer'!C24>0),'Gross margin per customer'!C24>0,IF('Gross margin per customer'!C24="","",'Gross margin per customer'!C24>0))),CEILING('Break-even inputs'!B8/('Gross margin per customer'!C24/'Billing assumptions'!B5),1),"") -> 46 | D9: =IF(IF(IF(ISERROR('Gross margin per customer'!D24>0),'Gross margin per customer'!D24>0,IF('Gross margin per customer'!D24="","",'Gross margin per customer'!D24>0))="",FALSE,IF(ISERROR('Gross margin per customer'!D24>0),'Gross margin per customer'!D24>0,IF('Gross margin per customer'!D24="","",'Gross margin per customer'!D24>0))),CEILING('Break-even inputs'!B8/('Gross margin per customer'!D24/'Billing assumptions'!B5),1),"") -> 12

Sheet Model inputs
A1: Model inputs
A2: Integration values are aggregated snapshots; raw source records are not included.
A4: Variables
A5: Variable / segment | B5: Value | C5: Value
A6: Card fee per invoice | B6: ='Billing assumptions'!B7 -> 0.3
A7: Card fee rate | B7: ='Billing assumptions'!B6 -> 0.029
A8: Monthly fixed costs | B8: ='Model inputs'!C11*'Model inputs'!C10+'Model inputs'!C12 -> 10500
A9: Repos per customer | B9: ='Billing assumptions'!B5 -> 1
A10: Founder cost per month · Break-even inputs | C10: ='Break-even inputs'!B6 -> 5000
A11: Founders · Break-even inputs | C11: ='Break-even inputs'!B5 -> 2
A12: Other fixed costs per month · Break-even inputs | C12: ='Break-even inputs'!B7 -> 500
A13: LLM cost per bisect | B13: ='Model inputs'!B17*'Model inputs'!B21 -> 0
A14: LLM cost per bisect > Bisect (v2) | B14: ='Model inputs'!B18*'Model inputs'!B22 -> 0.252
A15: LLM cost per bisect > Fix & verify | B15: ='Model inputs'!B19*'Model inputs'!B23 -> 0
A16: LLM cost per bisect > Localise | B16: ='Model inputs'!B20*'Model inputs'!B24 -> 0
A17: LLM cost per run | B17: 0
A18: LLM cost per run > Bisect (v2) | B18: ='Unit costs per bisect'!B5 -> 0.252
A19: LLM cost per run > Fix & verify | B19: ='Unit costs per bisect'!B6 -> 0.3337
A20: LLM cost per run > Localise | B20: ='Unit costs per bisect'!B7 -> 0.2002
A21: Stage run rate | B21: 0
A22: Stage run rate > Bisect (v2) | B22: ='Unit costs per bisect'!C5 -> 1
A23: Stage run rate > Fix & verify | B23: ='Unit costs per bisect'!C6 -> 0
A24: Stage run rate > Localise | B24: ='Unit costs per bisect'!C7 -> 0
A25: Founder cost per month · Break-even paying repos | B25: ='Break-even inputs'!B6 -> 5000
A26: Founders · Break-even paying repos | B26: ='Break-even inputs'!B5 -> 2
A27: Other fixed costs per month · Break-even paying repos | B27: ='Break-even inputs'!B7 -> 500
